pytrafikk/__init__.py
pytrafikk/client.py
pytrafikk/explore.py
pytrafikk/tests/__init__.py
pytrafikk/tests/test_client.py
pytrafikk/web/__init__.py
pytrafikk/web/app.py
pytrafikk-0.1.1.dist-info/LICENSE
pytrafikk-0.1.1.dist-info/METADATA
pytrafikk-0.1.1.dist-info/WHEEL
pytrafikk-0.1.1.dist-info/top_level.txt
pytrafikk-0.1.1.dist-info/RECORD
