Metadata-Version: 2.1
Name: pytrafikk
Version: 0.1.1
Summary: A Python client for Norwegian traffic data
Home-page: https://github.com/paulskeie/pytrafikk
Author: Paul Skeie
Author-email: paul.skeie@gmail.com
Classifier: Development Status :: 4 - Beta
Classifier: Intended Audience :: Developers
Classifier: License :: OSI Approved :: MIT License
Classifier: Programming Language :: Python :: 3
Classifier: Programming Language :: Python :: 3.9
Classifier: Programming Language :: Python :: 3.10
Classifier: Programming Language :: Python :: 3.11
Requires-Python: >=3.9
License-File: LICENSE
Requires-Dist: requests>=2.25.0
Requires-Dist: pandas>=1.3.0
Requires-Dist: flask>=2.0.0
Requires-Dist: folium>=0.12.0
Requires-Dist: plotly>=5.0.0
Requires-Dist: pandas>=1.3.0
Provides-Extra: dev
Requires-Dist: pytest>=6.0; extra == "dev"
Requires-Dist: black>=21.0; extra == "dev"
Requires-Dist: flake8>=3.9; extra == "dev"
